test_sdk_kv/__init__.py
test_sdk_kv-0.0.2.dist-info/METADATA
test_sdk_kv-0.0.2.dist-info/WHEEL
test_sdk_kv-0.0.2.dist-info/top_level.txt
test_sdk_kv-0.0.2.dist-info/RECORD
