Metadata-Version: 2.4
Name: test_sdk_kv
Version: 0.0.2
Summary: A very basic Python SDK
Requires-Python: >=3.7
Requires-Dist: requests
